trackerfit/__init__.py
trackerfit/factory.py
trackerfit/ejercicios/__init__.py
trackerfit/ejercicios/crunch_abdominal.py
trackerfit/ejercicios/curl_bicep.py
trackerfit/ejercicios/dip_tricep.py
trackerfit/ejercicios/ejercicio.py
trackerfit/ejercicios/elevacion_lateral.py
trackerfit/ejercicios/extension_cuadricep.py
trackerfit/ejercicios/flexion.py
trackerfit/ejercicios/press_militar.py
trackerfit/ejercicios/sentadilla.py
trackerfit/session/__init__.py
trackerfit/session/camera.py
trackerfit/session/manager.py
trackerfit/session/session.py
trackerfit/session/video.py
trackerfit/tracker/__init__.py
trackerfit/tracker/pose_tracker.py
trackerfit/utils/__init__.py
trackerfit/utils/angulos.py
trackerfit/utils/ejercicio_enum.py
trackerfit/utils/estado_ejercicio_enum.py
trackerfit/utils/lado_enum.py
trackerfit/utils/rotacion.py
trackerfit/utils/tipo_entrada_enum.py
trackerfit/utils/tipo_esfuerzo_enum.py
trackerfit-1.0.2.dist-info/licenses/LICENSE
trackerfit-1.0.2.dist-info/METADATA
trackerfit-1.0.2.dist-info/WHEEL
trackerfit-1.0.2.dist-info/top_level.txt
trackerfit-1.0.2.dist-info/RECORD
