Metadata-Version: 2.4
Name: trackerfit
Version: 1.0.2
Summary: Librería de visión artificial para seguimiento y conteo de repeticiones en ejercicios físicos usando MediaPipe.
Author-email: Alberto Ortega Vilchez <kesolesito@gmail.com>
License: MIT
Project-URL: Homepage, https://github.com/4lverto/trackerfit
Project-URL: Repository, https://github.com/4lverto/trackerfit
Project-URL: Issues, https://github.com/4lverto/trackerfit/issues
Requires-Python: >=3.10
License-File: LICENSE
Requires-Dist: opencv-python>=4.11
Requires-Dist: mediapipe<0.11,>=0.10.20
Requires-Dist: numpy<2.0,>=1.24
Dynamic: license-file
